{
   "vrp-gecode-lns": {
      "time": 0,
      "optimal": true,
      "obj": 220,
      "sol": [
         [
            10,
            4
         ],
         [
            7
         ],
         [],
         [],
         [
            8
         ],
         [
            1,
            3
         ],
         [
            5,
            6
         ],
         [
            2,
            9
         ]
      ],
      "_extras": {
         "statistics": {
            "compiler": {
               "paths": 0,
               "flatBoolVars": 1760,
               "flatIntVars": 805,
               "flatBoolConstraints": 728,
               "flatIntConstraints": 2028,
               "evaluatedReifiedConstraints": 192,
               "evaluatedHalfReifiedConstraints": 1304,
               "eliminatedImplications": 112,
               "method": "minimize",
               "flatTime": 0.161652
            },
            "solver": {
               "initTime": 0.0142124,
               "solveTime": 0.00848091,
               "solutions": 6,
               "variables": 2565,
               "propagators": 2756,
               "propagations": 81739,
               "nodes": 497,
               "failures": 1,
               "restarts": 6,
               "peakDepth": 80
            },
            "solution": {
               "nSolutions": 6
            }
         },
         "crash_reason": null,
         "time_to_last_solution": 0.222,
         "runner": "github-action"
      }
   },
   "vrp-gecode-lns-symm_weak": {
      "time": 0,
      "optimal": true,
      "obj": 220,
      "sol": [
         [],
         [
            5,
            7
         ],
         [
            10
         ],
         [],
         [
            1,
            3,
            9
         ],
         [
            8
         ],
         [
            2,
            4
         ],
         [
            6
         ]
      ],
      "_extras": {
         "statistics": {
            "compiler": {
               "paths": 0,
               "flatBoolVars": 1760,
               "flatIntVars": 805,
               "flatBoolConstraints": 728,
               "flatIntConstraints": 2033,
               "evaluatedReifiedConstraints": 192,
               "evaluatedHalfReifiedConstraints": 1304,
               "eliminatedImplications": 112,
               "method": "minimize",
               "flatTime": 0.171595
            },
            "solver": {
               "initTime": 0.0142862,
               "solveTime": 0.00475355,
               "solutions": 2,
               "variables": 2565,
               "propagators": 2761,
               "propagations": 42668,
               "nodes": 190,
               "failures": 13,
               "restarts": 3,
               "peakDepth": 85
            },
            "solution": {
               "nSolutions": 2
            }
         },
         "crash_reason": null,
         "time_to_last_solution": 0.229,
         "runner": "github-action"
      }
   },
   "vrp-gecode-lns-symm_strong": {
      "time": 0,
      "optimal": true,
      "obj": 220,
      "sol": [
         [],
         [
            10
         ],
         [
            8
         ],
         [
            7
         ],
         [
            5
         ],
         [
            4,
            3
         ],
         [
            2,
            6
         ],
         [
            9,
            1
         ]
      ],
      "_extras": {
         "statistics": {
            "compiler": {
               "paths": 0,
               "flatBoolVars": 2974,
               "flatIntVars": 833,
               "flatBoolConstraints": 1332,
               "flatIntConstraints": 2694,
               "evaluatedReifiedConstraints": 1104,
               "evaluatedHalfReifiedConstraints": 1326,
               "eliminatedImplications": 112,
               "method": "minimize",
               "flatTime": 0.191449
            },
            "solver": {
               "initTime": 0.0220346,
               "solveTime": 0.439003,
               "solutions": 3,
               "variables": 3807,
               "propagators": 4026,
               "propagations": 5401110,
               "nodes": 4749,
               "failures": 2128,
               "restarts": 49,
               "peakDepth": 87
            },
            "solution": {
               "nSolutions": 3
            }
         },
         "crash_reason": null,
         "time_to_last_solution": 0.703,
         "runner": "github-action"
      }
   },
   "vrp-chuffed": {
      "time": 0,
      "optimal": true,
      "obj": 220,
      "sol": [
         [
            9,
            10,
            6,
            3,
            5
         ],
         [
            8
         ],
         [
            2,
            4,
            7
         ],
         [
            1
         ],
         [],
         [],
         [],
         []
      ],
      "_extras": {
         "statistics": {
            "compiler": {
               "paths": 0,
               "flatBoolVars": 1760,
               "flatIntVars": 875,
               "flatBoolConstraints": 728,
               "flatIntConstraints": 2113,
               "evaluatedReifiedConstraints": 376,
               "evaluatedHalfReifiedConstraints": 1120,
               "eliminatedImplications": 112,
               "method": "minimize",
               "flatTime": 0.167661
            },
            "solver": {
               "nodes": 27664,
               "failures": 6931,
               "restarts": 82,
               "variables": 45637,
               "intVars": 963,
               "boolVariables": 44672,
               "propagators": 1330,
               "propagations": 2225986,
               "peakDepth": 357,
               "nogoods": 6931,
               "backjumps": 4700,
               "peakMem": 0.0,
               "time": 0.732,
               "initTime": 0.045,
               "solveTime": 0.687,
               "objective": 220,
               "optTime": 0.686,
               "baseMem": 0.0,
               "trailMem": 0.19,
               "randomSeed": 42
            },
            "solution": {
               "nSolutions": 46
            }
         },
         "crash_reason": null,
         "time_to_last_solution": 0.93,
         "runner": "github-action"
      }
   },
   "vrp-chuffed-lns-symm_weak": {
      "time": 0,
      "optimal": true,
      "obj": 220,
      "sol": [
         [
            9
         ],
         [
            5,
            6
         ],
         [],
         [
            1,
            2,
            4
         ],
         [
            3
         ],
         [
            8
         ],
         [
            10
         ],
         [
            7
         ]
      ],
      "_extras": {
         "statistics": {
            "compiler": {
               "paths": 0,
               "flatBoolVars": 1960,
               "flatIntVars": 875,
               "flatBoolConstraints": 918,
               "flatIntConstraints": 2223,
               "evaluatedReifiedConstraints": 531,
               "evaluatedHalfReifiedConstraints": 1120,
               "eliminatedImplications": 112,
               "method": "minimize",
               "flatTime": 0.174611
            },
            "solver": {
               "nodes": 2463,
               "failures": 566,
               "restarts": 12,
               "variables": 42303,
               "intVars": 963,
               "boolVariables": 41338,
               "propagators": 1545,
               "propagations": 332370,
               "peakDepth": 223,
               "nogoods": 566,
               "backjumps": 338,
               "peakMem": 0.0,
               "time": 0.142,
               "initTime": 0.048,
               "solveTime": 0.094,
               "objective": 220,
               "optTime": 0.094,
               "baseMem": 0.0,
               "trailMem": 0.19,
               "randomSeed": 42
            },
            "solution": {
               "nSolutions": 7
            }
         },
         "crash_reason": null,
         "time_to_last_solution": 0.348,
         "runner": "github-action"
      }
   },
   "vrp-chuffed-lns-symm_strong": {
      "time": 0,
      "optimal": true,
      "obj": 220,
      "sol": [
         [
            10,
            8,
            9
         ],
         [
            7
         ],
         [
            6
         ],
         [
            5
         ],
         [
            4
         ],
         [
            3
         ],
         [
            2
         ],
         [
            1
         ]
      ],
      "_extras": {
         "statistics": {
            "compiler": {
               "paths": 0,
               "flatBoolVars": 2974,
               "flatIntVars": 903,
               "flatBoolConstraints": 1880,
               "flatIntConstraints": 2779,
               "evaluatedReifiedConstraints": 1294,
               "evaluatedHalfReifiedConstraints": 1142,
               "eliminatedImplications": 112,
               "method": "minimize",
               "flatTime": 0.196361
            },
            "solver": {
               "nodes": 549,
               "failures": 102,
               "restarts": 3,
               "variables": 53215,
               "intVars": 991,
               "boolVariables": 52222,
               "propagators": 2584,
               "propagations": 133897,
               "peakDepth": 171,
               "nogoods": 102,
               "backjumps": 106,
               "peakMem": 0.0,
               "time": 0.098,
               "initTime": 0.071,
               "solveTime": 0.027,
               "objective": 220,
               "optTime": 0.026,
               "baseMem": 0.0,
               "trailMem": 0.19,
               "randomSeed": 42
            },
            "solution": {
               "nSolutions": 2
            }
         },
         "crash_reason": null,
         "time_to_last_solution": 0.337,
         "runner": "github-action"
      }
   },
   "vrp-gecode-lns2": {
      "time": 0,
      "optimal": true,
      "obj": 220,
      "sol": [
         [],
         [
            5,
            7
         ],
         [
            10
         ],
         [
            1
         ],
         [
            3,
            9
         ],
         [
            8
         ],
         [
            4,
            2
         ],
         [
            6
         ]
      ],
      "_extras": {
         "statistics": {
            "compiler": {
               "paths": 0,
               "flatBoolVars": 960,
               "flatIntVars": 718,
               "flatBoolConstraints": 568,
               "flatIntConstraints": 1221,
               "evaluatedReifiedConstraints": 112,
               "evaluatedHalfReifiedConstraints": 664,
               "eliminatedImplications": 112,
               "method": "minimize",
               "flatTime": 0.161715
            },
            "solver": {
               "initTime": 0.00991023,
               "solveTime": 0.00403277,
               "solutions": 3,
               "variables": 1678,
               "propagators": 1789,
               "propagations": 27174,
               "nodes": 241,
               "failures": 0,
               "restarts": 2,
               "peakDepth": 81
            },
            "solution": {
               "nSolutions": 3
            }
         },
         "crash_reason": null,
         "time_to_last_solution": 0.207,
         "runner": "github-action"
      }
   },
   "vrp-gecode-lns-symm_weak2": {
      "time": 0,
      "optimal": true,
      "obj": 220,
      "sol": [
         [],
         [
            5
         ],
         [
            10
         ],
         [
            3,
            2,
            4
         ],
         [
            1,
            9
         ],
         [
            8
         ],
         [
            6
         ],
         [
            7
         ]
      ],
      "_extras": {
         "statistics": {
            "compiler": {
               "paths": 0,
               "flatBoolVars": 1200,
               "flatIntVars": 798,
               "flatBoolConstraints": 728,
               "flatIntConstraints": 1466,
               "evaluatedReifiedConstraints": 192,
               "evaluatedHalfReifiedConstraints": 824,
               "eliminatedImplications": 112,
               "method": "minimize",
               "flatTime": 0.174237
            },
            "solver": {
               "initTime": 0.0119777,
               "solveTime": 0.00718852,
               "solutions": 3,
               "variables": 1998,
               "propagators": 2194,
               "propagations": 47565,
               "nodes": 268,
               "failures": 17,
               "restarts": 4,
               "peakDepth": 85
            },
            "solution": {
               "nSolutions": 3
            }
         },
         "crash_reason": null,
         "time_to_last_solution": 0.228,
         "runner": "github-action"
      }
   }
}